open_speech/__init__.py
open_speech/dataset.py
open_speech/datasplit.py
open_speech/multiset.py
open_speech/multisplit.py
open_speech/util.py
open_speech-5.5.dist-info/LICENSE.md
open_speech-5.5.dist-info/METADATA
open_speech-5.5.dist-info/WHEEL
open_speech-5.5.dist-info/top_level.txt
open_speech-5.5.dist-info/RECORD
