Metadata-Version: 2.1
Name: open-speech
Version: 5.5
Summary: Open Speech Datasets
Home-page: https://github.com/dimitry-ishenko-ml/open-speech
Author: Dimitry Ishenko
Author-email: dimitry.ishenko@gmail.com
License: UNKNOWN
Platform: UNKNOWN
Classifier: License :: OSI Approved :: GNU General Public License v3 (GPLv3)
Classifier: Operating System :: OS Independent
Classifier: Programming Language :: Python :: 3
Requires-Python: >=3.7
Requires-Dist: tensorflow
Requires-Dist: unidecode
